LICENSE
MANIFEST.in
README.md
VERSION
setup.cfg
setup.py
hola_mundo/__init__.py
hola_mundo/el_grito.py
hola_mundo/el_mundo.py
hola_mundo/main.py
hola_mundo.egg-info/PKG-INFO
hola_mundo.egg-info/SOURCES.txt
hola_mundo.egg-info/dependency_links.txt
hola_mundo.egg-info/requires.txt
hola_mundo.egg-info/top_level.txt
hola_mundo/util/__init__.py
hola_mundo/util/config.yaml
hola_mundo/util/config_loader.py