Metadata-Version: 1.1
Name: hola-mundo
Version: 0.0.3
Summary: Hola Mundo!
Home-page: https//github.com/neoinsanity/hola_mundo
Author: Raul Gonzalez
Author-email: mindbender@gmail.com
License: Apache License 2.0
Platform: UNKNOWN
Classifier: Development Status :: 3 - Alpha
Classifier: Intended Audience :: Developers
Classifier: License :: OSI Approved :: Apache Software License
Classifier: Programming Language :: Python :: 3
Classifier: Topic :: Software Development
